upeep80/__init__.py
upeep80/peephole.py
upeep80-0.2.0.dist-info/METADATA
upeep80-0.2.0.dist-info/WHEEL
upeep80-0.2.0.dist-info/top_level.txt
upeep80-0.2.0.dist-info/RECORD
