Metadata-Version: 2.4
Name: upeep80
Version: 0.2.0
Summary: Universal peephole and AST optimizer for 8080/Z80 compilers
Author: upeep80 project
License: GPLv2
Project-URL: Homepage, https://github.com/yourusername/upeep80
Project-URL: Repository, https://github.com/yourusername/upeep80
Project-URL: Documentation, https://github.com/yourusername/upeep80/tree/main/docs
Project-URL: Bug Tracker, https://github.com/yourusername/upeep80/issues
Keywords: compiler,optimization,z80,8080,peephole,ast,retro
Classifier: Development Status :: 3 - Alpha
Classifier: Intended Audience :: Developers
Classifier: License :: OSI Approved :: GNU General Public License v2 (GPLv2)
Classifier: Programming Language :: Python :: 3
Classifier: Programming Language :: Python :: 3.10
Classifier: Programming Language :: Python :: 3.11
Classifier: Programming Language :: Python :: 3.12
Classifier: Topic :: Software Development :: Compilers
Classifier: Topic :: Software Development :: Code Generators
Requires-Python: >=3.10
Provides-Extra: dev
Requires-Dist: pytest>=7.4.0; extra == "dev"
Requires-Dist: pytest-cov>=4.1.0; extra == "dev"
Requires-Dist: pytest-benchmark>=4.0.0; extra == "dev"
Requires-Dist: mypy>=1.5.0; extra == "dev"
Requires-Dist: black>=23.7.0; extra == "dev"
Requires-Dist: ruff>=0.0.285; extra == "dev"
